vibrationview_api-0.1.9.dist-info/licenses/LICENSE
vibrationviewapi/__init__.py
vibrationviewapi/comhelper.py
vibrationviewapi/config.py
vibrationviewapi/vibrationviewapi.py
vibrationviewapi/vibrationviewcommandline.py
vibrationviewapi/vv_enums.py
vibrationview_api-0.1.9.dist-info/METADATA
vibrationview_api-0.1.9.dist-info/WHEEL
vibrationview_api-0.1.9.dist-info/top_level.txt
vibrationview_api-0.1.9.dist-info/RECORD
