Metadata-Version: 2.4
Name: vibrationview-api
Version: 0.1.9
Summary: Python API for VibrationVIEW software
Author-email: Vibration Research Corporation <support@vibrationresearch.com>
License-Expression: MIT
Project-URL: Homepage, https://www.vibrationresearch.com/
Project-URL: Bug Tracker, https://github.com/vibrationresearch/vibrationview-api/issues
Project-URL: Source Code, https://github.com/vibrationresearch/vibrationview-api
Project-URL: Documentation, https://www.vibrationresearch.com/vibrationview-api/
Keywords: vibration,testing,VibrationVIEW,api
Classifier: Development Status :: 4 - Beta
Classifier: Intended Audience :: Science/Research
Classifier: Intended Audience :: Manufacturing
Classifier: Programming Language :: Python :: 3
Classifier: Programming Language :: Python :: 3.7
Classifier: Programming Language :: Python :: 3.8
Classifier: Programming Language :: Python :: 3.9
Classifier: Programming Language :: Python :: 3.10
Classifier: Topic :: Scientific/Engineering
Classifier: Topic :: Scientific/Engineering :: Physics
Classifier: Operating System :: Microsoft :: Windows
Requires-Python: >=3.7
License-File: LICENSE
Requires-Dist: pywin32>=300
Provides-Extra: dev
Requires-Dist: types-pywin32>=310; extra == "dev"
Requires-Dist: pytest>=6.0.0; extra == "dev"
Requires-Dist: black>=21.5b2; extra == "dev"
Requires-Dist: pylint>=2.8.2; extra == "dev"
Provides-Extra: test
Requires-Dist: pytest>=6.0.0; extra == "test"
Dynamic: license-file
